pipes_vis/__init__.py
pipes_vis/fix_wavelength_range_bug.py
pipes_vis/override_config.py
pipes_vis/plotting.py
pipes_vis/slider_params.py
pipes_vis/utils.py
pipes_vis/visualizer.py
pipes_vis-0.4.5.1.dist-info/licenses/LICENSE
pipes_vis-0.4.5.1.dist-info/METADATA
pipes_vis-0.4.5.1.dist-info/WHEEL
pipes_vis-0.4.5.1.dist-info/top_level.txt
pipes_vis-0.4.5.1.dist-info/RECORD
