Metadata-Version: 2.4
Name: pipes-vis
Version: 0.4.5.1
Summary: Small interactive GUI/visualizer tool for SPS spectra
Home-page: https://github.com/HinLeung622/pipes_vis
Author: Ho-Hin Leung
Author-email: hleung2@roe.ac.uk
Project-URL: Bug Tracker, https://github.com/HinLeung622/pipes_vis/issues
Classifier: Programming Language :: Python :: 3
Classifier: License :: OSI Approved :: GNU General Public License v3 (GPLv3)
Classifier: Operating System :: OS Independent
Requires-Python: >=3.6
License-File: LICENSE
Requires-Dist: bagpipes>=1.0.0
Requires-Dist: numpy>=1.14.2
Requires-Dist: astropy
Requires-Dist: matplotlib>=2.2.2
Requires-Dist: scipy
Dynamic: author
Dynamic: author-email
Dynamic: classifier
Dynamic: description
Dynamic: description-content-type
Dynamic: home-page
Dynamic: license-file
Dynamic: project-url
Dynamic: requires-dist
Dynamic: requires-python
Dynamic: summary
